odoo/addons/maintenance_equipment_scrap/README.rst
odoo/addons/maintenance_equipment_scrap/__init__.py
odoo/addons/maintenance_equipment_scrap/__manifest__.py
odoo/addons/maintenance_equipment_scrap/data/maintenance_data.xml
odoo/addons/maintenance_equipment_scrap/i18n/ca.po
odoo/addons/maintenance_equipment_scrap/i18n/es.po
odoo/addons/maintenance_equipment_scrap/i18n/it.po
odoo/addons/maintenance_equipment_scrap/i18n/maintenance_equipment_scrap.pot
odoo/addons/maintenance_equipment_scrap/i18n/zh_CN.po
odoo/addons/maintenance_equipment_scrap/models/__init__.py
odoo/addons/maintenance_equipment_scrap/models/maintenance_equipment.py
odoo/addons/maintenance_equipment_scrap/models/maintenance_equipment_category.py
odoo/addons/maintenance_equipment_scrap/readme/CONTRIBUTORS.rst
odoo/addons/maintenance_equipment_scrap/readme/DESCRIPTION.rst
odoo/addons/maintenance_equipment_scrap/security/ir.model.access.csv
odoo/addons/maintenance_equipment_scrap/static/description/icon.png
odoo/addons/maintenance_equipment_scrap/static/description/index.html
odoo/addons/maintenance_equipment_scrap/tests/__init__.py
odoo/addons/maintenance_equipment_scrap/tests/test_maintenance_equipment_scrap.py
odoo/addons/maintenance_equipment_scrap/views/maintenance_equipment.xml
odoo/addons/maintenance_equipment_scrap/views/maintenance_equipment_category.xml
odoo/addons/maintenance_equipment_scrap/wizard/__init__.py
odoo/addons/maintenance_equipment_scrap/wizard/scrap_equipment.py
odoo/addons/maintenance_equipment_scrap/wizard/scrap_equipment.xml
odoo14_addon_maintenance_equipment_scrap-14.0.1.0.2.dist-info/METADATA
odoo14_addon_maintenance_equipment_scrap-14.0.1.0.2.dist-info/WHEEL
odoo14_addon_maintenance_equipment_scrap-14.0.1.0.2.dist-info/top_level.txt
odoo14_addon_maintenance_equipment_scrap-14.0.1.0.2.dist-info/RECORD
